Metadata-Version: 1.0
Name: seismology
Version: 0.0.1
Summary: A package for seismic source inversion
Home-page: UNKNOWN
Author: Qipeng Bai
Author-email: bqpseismology@gmail.com
License: UNKNOWN
Keywords: seismology,eathquake,python
Platform: UNKNOWN
